{
  "yingcai": {
    "titles": [
      "admin",
      "新闻报道",
      "文件通知",
      "视频播报",
      "活动掠影",
      "导师风采",
      "学习资源"
    ],
    "cards": [
      "您好，请登录"
    ],
    "links": [
      "项目概况",
      "省级推广",
      "文件通知",
      "新闻报道",
      "学习中心",
      "师生天地",
      "意见反馈",
      "证书查询",
      "联系方式"
    ],
    "navItems": [
      "首页",
      "项目概况",
      "省级推广",
      "文件通知",
      "新闻报道",
      "学习中心",
      "师生天地",
      "意见反馈",
      "证书查询",
      "联系方式"
    ]
  },
  "kexueying": {
    "titles": [
      "admin",
      "查看更多",
      "开营第一课",
      "1x",
      "精彩回顾",
      "对话科学家",
      "分营动态\n查看更多",
      "云上资源\n查看更多",
      "内蒙古自治区青少年高校科学营呼和浩特市分营精彩瞬间",
      "2025 | 开营！怀揣科学梦想，拥抱星辰大海",
      "分营名录\n 搜索"
    ],
    "cards": [
      "您好，请登录",
      "名家大师报告",
      "科研动手实践"
    ],
    "links": []
  },
  "xinghuo": {
    "error": "page.goto: Timeout 30000ms exceeded.\nCall log:\n  - navigating to \"https://gxxhg-kp.cast.org.cn/front/home\", waiting until \"networkidle\"\n"
  }
}